gcd2.v
`timescale 1ns / 1ps
module gcd2(
    input clk,
    input rst,
    input start,
    input [15:0] a_in,
    input [15:0] b_in,
    output reg valid,
    output reg [15:0] out
);

    localparam IDLE    = 3'd0;
    localparam COMPARE = 3'd1;
    localparam A_GT_B  = 3'd2;
    localparam B_GT_A  = 3'd3;
    localparam EQUAL   = 3'd4;

    reg [2:0] state, nxt_state;
    reg [15:0] a, b;
    reg signed [16:0] y;

    always @(posedge clk) begin
        if (rst) begin
            state <= IDLE;
            a <= 0;
            b <= 0;
            valid <= 0;
            out <= 0;
        end else begin
            state <= nxt_state;

            case (state)
                IDLE: begin
                    valid <= 0;
                    if (start) begin
                        a <= a_in;
                        b <= b_in;
                    end
                end

                A_GT_B: begin
                    a <= a - b;
                end

                B_GT_A: begin
                    b <= b - a;
                end

                EQUAL: begin
                    valid <= 1;
                    valid <= 1;
                    if (a == 0 || b == 0)
                        out <= 0;
                    else
                        out <= a;
                end

                default: ;
            endcase
        end
    end

    // next state logic
    always @(*) begin
        nxt_state = state;

        y = $signed({1'b0, a}) - $signed({1'b0, b});

        case (state)
            IDLE: begin
                if (start)
                    nxt_state = COMPARE;
            end

            COMPARE: begin
                if(a == 0 || b == 0) 
                    nxt_state = EQUAL;
                else if (y > 0)
                    nxt_state = A_GT_B;
                else if (y < 0)
                    nxt_state = B_GT_A;
                else
                    nxt_state = EQUAL;
            end

            A_GT_B,
            B_GT_A: begin
                nxt_state = COMPARE;
            end

            EQUAL: begin
                nxt_state = IDLE;
            end

            default: nxt_state = IDLE;
        endcase
    end

endmodule

gcd3_top.v
`timescale 1ns / 1ps

module gcd3_top (
    input  wire clk,
    input  wire reset,
    input  wire start,
    input  wire [15:0] A,
    input  wire [15:0] B,
    input  wire [15:0] C,
    output reg valid,
    output reg [15:0] D
);

    reg s;
    reg start_gcd;
    wire valid_gcd;
    wire [15:0] gcd_out;

    reg [15:0] in1, in2;
    reg [15:0] result_ab;

    always @(*) begin
        if (s == 0) begin
            in1 = A;
            in2 = B;
        end else begin
            in1 = result_ab;
            in2 = C;
        end
    end

    localparam IDLE = 2'd0,
               FIRST_PASS = 2'd1,
               SECOND_PASS = 2'd2,
               DONE = 2'd3;

    reg [1:0] state, next_state;

    always @(posedge clk) begin
        if (reset) begin
            state <= IDLE;
            start_gcd <= 0;
            s <= 0;
            result_ab <= 0;
            valid <= 0;
            D <= 0;
        end else begin
            state <= next_state;

            case (state)
                IDLE: begin
                    valid <= 0;
                    if (start) begin
                        start_gcd <= 1;
                        s <= 0;
                    end
                end

                FIRST_PASS: begin
                    start_gcd <= 0;
                    if (valid_gcd) begin
                        result_ab <= gcd_out;
                        start_gcd <= 1;
                        s <= 1;
                    end
                end

                SECOND_PASS: begin
                    start_gcd <= 0;
                    if (valid_gcd) begin
                        D <= gcd_out;
                        valid <= 1;
                    end
                end

                DONE: begin
                    start_gcd <= 0;
                    s <= 0;
                end
            endcase
        end
    end

    always @(*) begin
        next_state = state;
        case (state)
            IDLE: if (start) next_state = FIRST_PASS;
            FIRST_PASS: if (valid_gcd) next_state = SECOND_PASS;
            SECOND_PASS: if (valid_gcd) next_state = DONE;
            DONE: next_state = IDLE;
        endcase
    end

    gcd2 cal(
        .clk(clk),
        .rst(reset),
        .start(start_gcd),
        .a_in(in1),
        .b_in(in2),
        .valid(valid_gcd),
        .out(gcd_out)
    );

endmodule

gcd3_tb.v
`timescale 1ns / 1ps

module gcd3_tb();
    parameter CLK_PERIOD = 10;

    reg clk, reset, start;
    reg [15:0] A, B, C;
    wire valid;
    wire [15:0] D;

    gcd3_top uut (
        .clk(clk), .reset(reset), .start(start),
        .A(A), .B(B), .C(C), .valid(valid), .D(D)
    );

    initial begin
        clk = 0;
        forever #(CLK_PERIOD/2) clk = ~clk;
    end

    initial begin
        reset = 1; start = 0; A = 0; B = 0; C = 0;
        #(CLK_PERIOD*2); reset = 0; #(CLK_PERIOD*2);

        run_test(24, 36, 48);
        run_test(15, 25, 35);
        run_test(100, 125, 150);
        run_test(17, 19, 23);
        run_test(0, 36, 48);

        #(CLK_PERIOD*10);
        $finish;
    end

    task run_test(input [15:0] a, b, c);
        begin
            A = a; B = b; C = c;
            start = 1; #(CLK_PERIOD); start = 0;
            wait(valid); #(CLK_PERIOD);
            $display("Result = %d", D);
            reset = 1; #(CLK_PERIOD*2); reset = 0; #(CLK_PERIOD*2);
        end
    endtask
endmodule

gcd3_tb.vcd
$version Generated by VerilatedVcd $end
$timescale 1ps $end
 $scope module $rootio $end
 $upscope $end
 $scope module gcd3_tb $end
  $var wire 1 5 clk $end
  $var wire 1 # reset $end
  $var wire 1 $ start $end
  $var wire 16 % A [15:0] $end
  $var wire 16 & B [15:0] $end
  $var wire 16 ' C [15:0] $end
  $var wire 16 ( D [15:0] $end
  $var wire 1 ) valid $end
  $scope module uut $end
   $var wire 1 5 clk $end
   $var wire 1 # reset $end
   $var wire 1 $ start $end
   $var wire 16 % A [15:0] $end
   $var wire 16 & B [15:0] $end
   $var wire 16 ' C [15:0] $end
   $var wire 1 ) valid $end
   $var wire 16 ( D [15:0] $end
   $var wire 1 * s $end
   $var wire 1 + start_gcd $end
   $var wire 1 , valid_gcd $end
   $var wire 16 - gcd_out [15:0] $end
   $var wire 16 6 in1 [15:0] $end
   $var wire 16 7 in2 [15:0] $end
   $var wire 16 . result_ab [15:0] $end
   $var wire 2 9 IDLE [1:0] $end
   $var wire 2 : FIRST_PASS [1:0] $end
   $var wire 2 ; SECOND_PASS [1:0] $end
   $var wire 2 < DONE [1:0] $end
   $var wire 2 / state [1:0] $end
   $var wire 2 8 next_state [1:0] $end
   $scope module cal $end
    $var wire 1 5 clk $end
    $var wire 1 # rst $end
    $var wire 1 + start $end
    $var wire 16 6 a_in [15:0] $end
    $var wire 16 7 b_in [15:0] $end
    $var wire 1 , valid $end
    $var wire 16 - out [15:0] $end
    $var wire 3 = IDLE [2:0] $end
    $var wire 3 > COMPARE [2:0] $end
    $var wire 3 ? A_GT_B [2:0] $end
    $var wire 3 @ B_GT_A [2:0] $end
    $var wire 3 A EQUAL [2:0] $end
    $var wire 3 0 state [2:0] $end
    $var wire 3 1 nxt_state [2:0] $end
    $var wire 16 2 a [15:0] $end
    $var wire 16 3 b [15:0] $end
    $var wire 17 4 y [16:0] $end
   $upscope $end
  $upscope $end
 $upscope $end
$enddefinitions $end


#0
1#
0$
b0000000000000000 %
b0000000000000000 &
b0000000000000000 '
b0000000000000000 (
0)
0*
0+
0,
b0000000000000000 -
b0000000000000000 .
b00 /
b000 0
b000 1
b0000000000000000 2
b0000000000000000 3
b00000000000000000 4
05
b0000000000000000 6
b0000000000000000 7
b00 8
b00 9
b01 :
b10 ;
b11 <
b000 =
b001 >
b010 ?
b011 @
b100 A
#5000
15
#10000
05
#15000
15
#20000
0#
05
#25000
15
#30000
1$
b0000000000110000 %
b0000000000010010 &
b0000000000011110 '
05
b0000000000110000 6
b0000000000010010 7
b01 8
#35000
1+
b01 /
b001 1
15
#40000
0$
05
#45000
0+
b001 0
b010 1
b0000000000110000 2
b0000000000010010 3
b00000000000011110 4
15
#50000
05
#55000
b010 0
b001 1
15
#60000
05
#65000
b001 0
b010 1
b0000000000011110 2
b00000000000001100 4
15
#70000
05
#75000
b010 0
b001 1
15
#80000
05
#85000
b001 0
b011 1
b0000000000001100 2
b11111111111111010 4
15
#90000
05
#95000
b011 0
b001 1
15
#100000
05
#105000
b001 0
b010 1
b0000000000000110 3
b00000000000000110 4
15
#110000
05
#115000
b010 0
b001 1
15
#120000
05
#125000
b001 0
b100 1
b0000000000000110 2
b00000000000000000 4
15
#130000
05
#135000
b100 0
b000 1
15
#140000
05
#145000
1,
b0000000000000110 -
b000 0
15
b10 8
#150000
05
#155000
1*
1+
0,
b0000000000000110 .
b10 /
b001 1
15
b0000000000000110 6
b0000000000011110 7
#160000
05
#165000
0+
b001 0
b011 1
b0000000000011110 3
b11111111111101000 4
15
#170000
05
#175000
b011 0
b001 1
15
#180000
05
#185000
b001 0
b011 1
b0000000000011000 3
b11111111111101110 4
15
#190000
05
#195000
b011 0
b001 1
15
#200000
05
#205000
b001 0
b011 1
b0000000000010010 3
b11111111111110100 4
15
#210000
05
#215000
b011 0
b001 1
15
#220000
05
#225000
b001 0
b011 1
b0000000000001100 3
b11111111111111010 4
15
#230000
05
#235000
b011 0
b001 1
15
#240000
05
#245000
b001 0
b100 1
b0000000000000110 3
b00000000000000000 4
15
#250000
05
#255000
b100 0
b000 1
15
#260000
05
#265000
1,
b000 0
15
b11 8
#270000
05
#275000
b0000000000000110 (
1)
0,
b11 /
15
b00 8
#280000
05
#285000
0*
b00 /
15
b0000000000110000 6
b0000000000010010 7
#290000
1#
05
#295000
b0000000000000000 (
0)
b0000000000000000 -
b0000000000000000 .
b0000000000000000 2
b0000000000000000 3
15
#300000
0#
05
#305000
15
#310000
1$
b0000000001100100 %
b0000000000011001 &
b0000000000110010 '
05
b0000000001100100 6
b0000000000011001 7
b01 8
#315000
1+
b01 /
b001 1
15
#320000
0$
05
#325000
0+
b001 0
b010 1
b0000000001100100 2
b0000000000011001 3
b00000000001001011 4
15
#330000
05
#335000
b010 0
b001 1
15
#340000
05
#345000
b001 0
b010 1
b0000000001001011 2
b00000000000110010 4
15
#350000
05
#355000
b010 0
b001 1
15
#360000
05
#365000
b001 0
b010 1
b0000000000110010 2
b00000000000011001 4
15
#370000
05
#375000
b010 0
b001 1
15
#380000
05
#385000
b001 0
b100 1
b0000000000011001 2
b00000000000000000 4
15
#390000
05
#395000
b100 0
b000 1
15
#400000
05
#405000
1,
b0000000000011001 -
b000 0
15
b10 8
#410000
05
#415000
1*
1+
0,
b0000000000011001 .
b10 /
b001 1
15
b0000000000011001 6
b0000000000110010 7
#420000
05
#425000
0+
b001 0
b011 1
b0000000000110010 3
b11111111111100111 4
15
#430000
05
#435000
b011 0
b001 1
15
#440000
05
#445000
b001 0
b100 1
b0000000000011001 3
b00000000000000000 4
15
#450000
05
#455000
b100 0
b000 1
15
#460000
05
#465000
1,
b000 0
15
b11 8
#470000
05
#475000
b0000000000011001 (
1)
0,
b11 /
15
b00 8
#480000
05
#485000
0*
b00 /
15
b0000000001100100 6
b0000000000011001 7
#490000
1$
b0000000000000111 %
b0000000000001101 &
b0000000000010011 '
05
b0000000000000111 6
b0000000000001101 7
b01 8
#495000
0)
1+
b01 /
b001 1
15
#500000
0$
05
#505000
0+
b001 0
b011 1
b0000000000000111 2
b0000000000001101 3
b11111111111111010 4
15
#510000
05
#515000
b011 0
b001 1
15
#520000
05
#525000
b001 0
b010 1
b0000000000000110 3
b00000000000000001 4
15
#530000
05
#535000
b010 0
b001 1
15
#540000
05
#545000
b001 0
b011 1
b0000000000000001 2
b11111111111111011 4
15
#550000
05
#555000
b011 0
b001 1
15
#560000
05
#565000
b001 0
b011 1
b0000000000000101 3
b11111111111111100 4
15
#570000
05
#575000
b011 0
b001 1
15
#580000
05
#585000
b001 0
b011 1
b0000000000000100 3
b11111111111111101 4
15
#590000
05
#595000
b011 0
b001 1
15
#600000
05
#605000
b001 0
b011 1
b0000000000000011 3
b11111111111111110 4
15
#610000
05
#615000
b011 0
b001 1
15
#620000
05
#625000
b001 0
b011 1
b0000000000000010 3
b11111111111111111 4
15
#630000
05
#635000
b011 0
b001 1
15
#640000
05
#645000
b001 0
b100 1
b0000000000000001 3
b00000000000000000 4
15
#650000
05
#655000
b100 0
b000 1
15
#660000
05
#665000
1,
b0000000000000001 -
b000 0
15
b10 8
#670000
05
#675000
1*
1+
0,
b0000000000000001 .
b10 /
b001 1
15
b0000000000000001 6
b0000000000010011 7
#680000
05
#685000
0+
b001 0
b011 1
b0000000000010011 3
b11111111111101110 4
15
#690000
05
#695000
b011 0
b001 1
15
#700000
05
#705000
b001 0
b011 1
b0000000000010010 3
b11111111111101111 4
15
#710000
05
#715000
b011 0
b001 1
15
#720000
05
#725000
b001 0
b011 1
b0000000000010001 3
b11111111111110000 4
15
#730000
05
#735000
b011 0
b001 1
15
#740000
05
#745000
b001 0
b011 1
b0000000000010000 3
b11111111111110001 4
15
#750000
05
#755000
b011 0
b001 1
15
#760000
05
#765000
b001 0
b011 1
b0000000000001111 3
b11111111111110010 4
15
#770000
05
#775000
b011 0
b001 1
15
#780000
05
#785000
b001 0
b011 1
b0000000000001110 3
b11111111111110011 4
15
#790000
05
#795000
b011 0
b001 1
15
#800000
05
#805000
b001 0
b011 1
b0000000000001101 3
b11111111111110100 4
15
#810000
05
#815000
b011 0
b001 1
15
#820000
05
#825000
b001 0
b011 1
b0000000000001100 3
b11111111111110101 4
15
#830000
05
#835000
b011 0
b001 1
15
#840000
05
#845000
b001 0
b011 1
b0000000000001011 3
b11111111111110110 4
15
#850000
05
#855000
b011 0
b001 1
15
#860000
05
#865000
b001 0
b011 1
b0000000000001010 3
b11111111111110111 4
15
#870000
05
#875000
b011 0
b001 1
15
#880000
05
#885000
b001 0
b011 1
b0000000000001001 3
b11111111111111000 4
15
#890000
05
#895000
b011 0
b001 1
15
#900000
05
#905000
b001 0
b011 1
b0000000000001000 3
b11111111111111001 4
15
#910000
05
#915000
b011 0
b001 1
15
#920000
05
#925000
b001 0
b011 1
b0000000000000111 3
b11111111111111010 4
15
#930000
05
#935000
b011 0
b001 1
15
#940000
05
#945000
b001 0
b011 1
b0000000000000110 3
b11111111111111011 4
15
#950000
05
#955000
b011 0
b001 1
15
#960000
05
#965000
b001 0
b011 1
b0000000000000101 3
b11111111111111100 4
15
#970000
05
#975000
b011 0
b001 1
15
#980000
05
#985000
b001 0
b011 1
b0000000000000100 3
b11111111111111101 4
15
#990000
05
#995000
b011 0
b001 1
15
#1000000
05
#1005000
b001 0
b011 1
b0000000000000011 3
b11111111111111110 4
15
#1010000
05
#1015000
b011 0
b001 1
15
#1020000
05
#1025000
b001 0
b011 1
b0000000000000010 3
b11111111111111111 4
15
#1030000
05
#1035000
b011 0
b001 1
15
#1040000
05
#1045000
b001 0
b100 1
b0000000000000001 3
b00000000000000000 4
15
#1050000
05
#1055000
b100 0
b000 1
15
#1060000
05
#1065000
1,
b000 0
15
b11 8
#1070000
05
#1075000
b0000000000000001 (
1)
0,
b11 /
15
b00 8
#1080000
05
#1085000
0*
b00 /
15
b0000000000000111 6
b0000000000001101 7
#1090000
1$
b0000000000000000 %
b0000000000000000 &
b0000000000000000 '
05
b0000000000000000 6
b0000000000000000 7
b01 8
#1095000
0)
1+
b01 /
b001 1
15
#1100000
0$
05
#1105000
0+
b001 0
b100 1
b0000000000000000 2
b0000000000000000 3
15
#1110000
05
#1115000
b100 0
b000 1
15
#1120000
05
#1125000
1,
b0000000000000000 -
b000 0
15
b10 8
#1130000
05
#1135000
1*
1+
0,
b0000000000000000 .
b10 /
b001 1
15
#1140000
05
#1145000
0+
b001 0
b100 1
15
#1150000
05
#1155000
b100 0
b000 1
15
#1160000
05
#1165000
1,
b000 0
15
b11 8
#1170000
05
#1175000
b0000000000000000 (
1)
0,
b11 /
15
b00 8
#1180000
05
#1185000
0*
b00 /
15
#1190000
1$
b0000000000011000 %
b0000000000100100 &
b0000000000111100 '
05
b0000000000011000 6
b0000000000100100 7
b01 8
#1195000
0)
1+
b01 /
b001 1
15
#1200000
0$
05
#1205000
0+
b001 0
b011 1
b0000000000011000 2
b0000000000100100 3
b11111111111110100 4
15
#1210000
05
#1215000
1#
b00 /
b000 0
b000 1
b0000000000000000 2
b0000000000000000 3
b00000000000000000 4
15
b00 8
#1220000
0#
05
#1225000
15
#1230000
05
#1235000
15
#1240000
05
#1245000
15
#1250000
1$
05
b01 8
#1255000
1+
b01 /
b001 1
15
#1260000
0$
05
#1265000
0+
b001 0
b011 1
b0000000000011000 2
b0000000000100100 3
b11111111111110100 4
15
#1270000
05
#1275000
b011 0
b001 1
15
#1280000
05
#1285000
b001 0
b010 1
b0000000000001100 3
b00000000000001100 4
15
#1290000
05
#1295000
b010 0
b001 1
15
#1300000
05
#1305000
b001 0
b100 1
b0000000000001100 2
b00000000000000000 4
15
#1310000
05
#1315000
b100 0
b000 1
15
#1320000
05
#1325000
1,
b0000000000001100 -
b000 0
15
b10 8
#1330000
05
#1335000
1*
1+
0,
b0000000000001100 .
b10 /
b001 1
15
b0000000000001100 6
b0000000000111100 7
#1340000
05
#1345000
0+
b001 0
b011 1
b0000000000111100 3
b11111111111010000 4
15
#1350000
05
#1355000
b011 0
b001 1
15
#1360000
05
#1365000
b001 0
b011 1
b0000000000110000 3
b11111111111011100 4
15
#1370000
05
#1375000
b011 0
b001 1
15
#1380000
05
#1385000
b001 0
b011 1
b0000000000100100 3
b11111111111101000 4
15
#1390000
05
#1395000
b011 0
b001 1
15
#1400000
05
#1405000
b001 0
b011 1
b0000000000011000 3
b11111111111110100 4
15
#1410000
05
#1415000
b011 0
b001 1
15
#1420000
05
#1425000
b001 0
b100 1
b0000000000001100 3
b00000000000000000 4
15
#1430000
05
#1435000
b100 0
b000 1
15
#1440000
05
#1445000
1,
b000 0
15
b11 8
#1450000
05
#1455000
b0000000000001100 (
1)
0,
b11 /
15
b00 8
#1460000
05
#1465000
0*
b00 /
15
b0000000000011000 6
b0000000000100100 7
